audio_samples-0.1.1.dist-info/METADATA
audio_samples-0.1.1.dist-info/WHEEL
audio_samples-0.1.1.dist-info/licenses/LICENSE
audio_samples/__init__.py
audio_samples/__init__.pyi
audio_samples/audio_samples.cpython-313-x86_64-linux-gnu.so
audio_samples/benching.ipynb
audio_samples/benchmark_latex_tables.tex
audio_samples/csv_processing.ipynb
audio_samples/generation.pyi
audio_samples/io.pyi
audio_samples/py.typed
audio_samples-0.1.1.dist-info/RECORD
