Metadata-Version: 2.4
Name: audio_samples
Version: 0.1.1
Classifier: Development Status :: 4 - Beta
Classifier: Intended Audience :: Developers
Classifier: Intended Audience :: Science/Research
Classifier: License :: OSI Approved :: MIT License
Classifier: Operating System :: OS Independent
Classifier: Programming Language :: Python :: 3
Classifier: Programming Language :: Python :: 3.8
Classifier: Programming Language :: Python :: 3.9
Classifier: Programming Language :: Python :: 3.10
Classifier: Programming Language :: Python :: 3.11
Classifier: Programming Language :: Python :: 3.12
Classifier: Programming Language :: Python :: 3.13
Classifier: Programming Language :: Python :: Implementation :: CPython
Classifier: Programming Language :: Python :: Implementation :: PyPy
Classifier: Programming Language :: Rust
Classifier: Topic :: Multimedia :: Sound/Audio
Classifier: Topic :: Multimedia :: Sound/Audio :: Analysis
Classifier: Topic :: Scientific/Engineering
Classifier: Topic :: Scientific/Engineering :: Information Analysis
Classifier: Topic :: Software Development :: Libraries :: Python Modules
Classifier: Typing :: Typed
Requires-Dist: numpy>=1.24.4
Requires-Dist: sphinx>=7.0.0 ; extra == 'docs'
Requires-Dist: sphinx-autodoc-typehints>=1.24.0 ; extra == 'docs'
Requires-Dist: sphinx-rtd-theme>=1.3.0 ; extra == 'docs'
Requires-Dist: myst-parser>=2.0.0 ; extra == 'docs'
Requires-Dist: sphinx-copybutton>=0.5.0 ; extra == 'docs'
Provides-Extra: docs
License-File: LICENSE
Summary: Python bindings for the AudioSamples Rust ecosystem - fast, type-safe audio processing with automatic metadata coordination
Keywords: audio,signal-processing,multimedia,rust,performance
Home-Page: https://github.com/jmg049/audio_samples_python
Author: Jack Geraghty (jmg049) <jgeraghty049@gmail.com>
Author-email: "Jack Geraghty (jmg049)" <jgeraghty049@gmail.com>
Maintainer-email: "Jack Geraghty (jmg049)" <jgeraghty049@gmail.com>
License: MIT
Requires-Python: >=3.8
Project-URL: Homepage, https://github.com/jmg049/audio_samples_python
Project-URL: Documentation, https://jmg049.github.io/audio_samples_python
Project-URL: Repository, https://github.com/jmg049/audio_samples_python
Project-URL: Bug Reports, https://github.com/jmg049/audio_samples_python/issues
